LICENSE
pika_pydantic/__init__.py
pika_pydantic/channel.py
pika_pydantic/exceptions.py
pika_pydantic/model.py
pika_pydantic/queues.py
pika_pydantic-0.1.4.dist-info/LICENSE
pika_pydantic-0.1.4.dist-info/WHEEL
pika_pydantic-0.1.4.dist-info/METADATA
pika_pydantic-0.1.4.dist-info/RECORD
