Metadata-Version: 2.1
Name: pika-pydantic
Version: 0.1.4
Summary: An opinionated Python implementation of the Producer-Consumer Pattern using RabbitMQ on top of the Python pika and pydantic libraries.
Home-page: https://github.com/ttamg/pika-pydantic
License: MIT
Keywords: pika,pydantic,rabbitmq
Author: Matt Gosden
Author-email: mdgosden@gmail.com
Requires-Python: >=3.8,<4.0
Classifier: License :: OSI Approved :: MIT License
Classifier: Operating System :: OS Independent
Classifier: Programming Language :: Python :: 3
Classifier: Programming Language :: Python :: 3.10
Classifier: Programming Language :: Python :: 3.8
Classifier: Programming Language :: Python :: 3.9
Classifier: Topic :: Communications
Requires-Dist: aenum (>=3.1.11,<4.0.0)
Requires-Dist: pika (>=1.2.1,<2.0.0)
Requires-Dist: pydantic (>=1.9.1,<2.0.0)
Project-URL: Repository, https://github.com/ttamg/pika-pydantic
